maximus_heapimus/__init__.py
maximus_heapimus/max_heap.py
maximus_heapimus/test.py
maximus_heapimus-0.1.0.dist-info/METADATA
maximus_heapimus-0.1.0.dist-info/WHEEL
maximus_heapimus-0.1.0.dist-info/RECORD
