Metadata-Version: 2.1
Name: maximus-heapimus
Version: 0.1.0
Summary: 
Author: Aryan Gandhi
Author-email: aryandgandhi@gmail.com
Requires-Python: >=3.12,<4.0
Classifier: Programming Language :: Python :: 3
Classifier: Programming Language :: Python :: 3.12
Requires-Dist: pytest (>=8.3.3,<9.0.0)
